mutax/__init__.py
mutax/py.typed
mutax-0.4.3.dist-info/licenses/LICENSE.txt
mutax-0.4.3.dist-info/WHEEL
mutax-0.4.3.dist-info/METADATA
mutax-0.4.3.dist-info/RECORD
