Metadata-Version: 2.4
Name: mutax
Version: 0.4.3
Summary: Evolutionary optimization algorithms in JAX
Author: Gabriel S. Gerlero
Author-email: Gabriel S. Gerlero <ggerlero@cimec.unl.edu.ar>
License-Expression: Apache-2.0
License-File: LICENSE.txt
Classifier: Development Status :: 4 - Beta
Classifier: Intended Audience :: Developers
Classifier: Intended Audience :: Science/Research
Classifier: License :: OSI Approved :: Apache Software License
Classifier: Programming Language :: Python
Classifier: Programming Language :: Python :: 3
Classifier: Programming Language :: Python :: 3.10
Classifier: Programming Language :: Python :: 3.11
Classifier: Programming Language :: Python :: 3.12
Classifier: Programming Language :: Python :: 3.13
Classifier: Programming Language :: Python :: 3.14
Classifier: Topic :: Scientific/Engineering :: Mathematics
Classifier: Topic :: Software Development :: Libraries
Classifier: Typing :: Typed
Classifier: Operating System :: OS Independent
Requires-Dist: equinox>=0.12.1,<0.14
Requires-Dist: jax>=0.5,<0.8
Requires-Dist: parajax>=0.2,<0.3
Requires-Python: >=3.10
Project-URL: Documentation, https://mutax.readthedocs.io
Project-URL: Homepage, https://github.com/gerlero/mutax
Project-URL: Repository, https://github.com/gerlero/mutax
